{
    "meetingsList": [
        {
            "title": "Hello World",
            "room": "Room - 666" ,
            "time": "12:00 - 15:00"
        },
        {
            "title": "Hello World",
            "room": "Room - 666" ,
            "time": "12:00 - 15:00"
        },
        {
            "title": "Hello World",
            "room": "Room - 666" ,
            "time": "12:00 - 15:00"
        },
        {
            "title": "Hello World",
            "room": "Room - 666" ,
            "time": "12:00 - 15:00"
        }
    ]
}
